mgost/MML2OMML.xsl
mgost/__init__.py
mgost/__main__.py
mgost/_base.docx
mgost/cli.py
mgost/context.py
mgost/exceptions.py
mgost/internet_connector.py
mgost/macros/__init__.py
mgost/macros/_exceptions.py
mgost/macros/_flags.py
mgost/macros/_mixins.py
mgost/macros/color.py
mgost/macros/comment.py
mgost/macros/count_formulas.py
mgost/macros/count_images.py
mgost/macros/count_tables.py
mgost/macros/formula.py
mgost/macros/formula_describe.py
mgost/macros/highlight_color.py
mgost/macros/listing.py
mgost/macros/mention.py
mgost/macros/print_plain_text.py
mgost/macros/set_list_digit.py
mgost/macros/set_list_marker.py
mgost/macros/store_var.py
mgost/macros/store_var_return.py
mgost/macros/table_name.py
mgost/macros/todo.py
mgost/macros/var.py
mgost/md_converter/__init__.py
mgost/md_converter/exceptions.py
mgost/md_converter/parser.py
mgost/post_processors/__init__.py
mgost/post_processors/headings_numbering/__init__.py
mgost/post_processors/internal_links/__init__.py
mgost/post_processors/sources/__init__.py
mgost/post_processors/sources_from_url/__init__.py
mgost/source_converters/__init__.py
mgost/source_converters/_base.py
mgost/source_converters/arXiv.py
mgost/source_converters/default.py
mgost/types/abstract.py
mgost/types/bases.py
mgost/types/functions.py
mgost/types/lists.py
mgost/types/low_functions.py
mgost/types/macros.py
mgost/types/media.py
mgost/types/mixins.py
mgost/types/run.py
mgost/types/simple.py
mgost/types/complex/formula_describe.py
mgost/types/complex/sources.py
mgost-1.4.1.dist-info/METADATA
mgost-1.4.1.dist-info/WHEEL
mgost-1.4.1.dist-info/entry_points.txt
mgost-1.4.1.dist-info/licenses/LICENSE
mgost-1.4.1.dist-info/RECORD
