Metadata-Version: 2.4
Name: mgost
Version: 1.4.1
Summary: Конвертер MD файлов в ГОСТ стандарт
Project-URL: homepage, https://github.com/ArtichaTM/MarkdownGost
Author-email: Геворкян Артём <tima-1324@mail.ru>
License: GNUv3
License-File: LICENSE
Classifier: Development Status :: 5 - Production/Stable
Classifier: Environment :: Console
Classifier: Intended Audience :: Information Technology
Classifier: License :: OSI Approved :: GNU General Public License v3 (GPLv3)
Classifier: Natural Language :: Russian
Classifier: Operating System :: Microsoft :: Windows
Classifier: Operating System :: POSIX :: Linux
Classifier: Programming Language :: Python
Classifier: Programming Language :: Python :: 3
Classifier: Programming Language :: Python :: 3 :: Only
Classifier: Programming Language :: Python :: 3.12
Classifier: Topic :: Office/Business
Classifier: Topic :: Text Processing :: Markup
Classifier: Topic :: Text Processing :: Markup :: HTML
Classifier: Topic :: Text Processing :: Markup :: LaTeX
Classifier: Topic :: Text Processing :: Markup :: Markdown
Requires-Python: >=3.12
Requires-Dist: latex2mathml
Requires-Dist: marko>=2.1.2
Requires-Dist: pillow>=10.4.0
Requires-Dist: python-docx>=1.1.2
Requires-Dist: requests
Requires-Dist: sympy>=1.13.3
Provides-Extra: build
Requires-Dist: build; extra == 'build'
Provides-Extra: tests
Requires-Dist: flake8; extra == 'tests'
